brooklyn/__init__.py
brooklyn/__main__.py
brooklyn/libs/coexpression.py
brooklyn/libs/parse.py
brooklyn/libs/summary.py
brooklyn/rScripts/brooklynPlot.R
brooklyn_plot/__init__.py
brooklyn_plot/__main__.py
brooklyn_plot/libs/__init__.py
brooklyn_plot/libs/coexpression.py
brooklyn_plot/libs/parse.py
brooklyn_plot/libs/rbaco.py
brooklyn_plot/libs/summary.py
brooklyn_plot/rScripts/__init__.py
brooklyn_plot/rScripts/brooklynPlot.R
brooklyn_plot-0.0.4.dist-info/LICENSE
brooklyn_plot-0.0.4.dist-info/METADATA
brooklyn_plot-0.0.4.dist-info/WHEEL
brooklyn_plot-0.0.4.dist-info/entry_points.txt
brooklyn_plot-0.0.4.dist-info/top_level.txt
brooklyn_plot-0.0.4.dist-info/RECORD
