Metadata-Version: 2.1
Name: brooklyn-plot
Version: 0.0.4
Summary: Gene co-expression and transcriptional bursting pattern recognition tool in single cell/nucleus RNA-sequencing data
Home-page: https://github.com/arunhpatil/brooklyn/
Author: Arun Patil, Matthew McCall and Marc Halushka
Author-email: halushm@ccf.org
License: MIT
Keywords: brooklyn,single cell,single nucleus,single cell-RNA,single nucleus-RNA,RNA analysis,cellxgene,RNA-seq,bioinformatics tools,co-expression,transcriptional bursting,sc-RNAseq,sn-RNAseq
Classifier: Development Status :: 1 - Planning
Classifier: Environment :: Console
Classifier: Intended Audience :: Science/Research
Classifier: License :: OSI Approved :: MIT License
Classifier: Natural Language :: English
Classifier: Programming Language :: Python :: 3.8
Classifier: Topic :: Scientific/Engineering :: Bio-Informatics
Requires-Python: >=3.7
License-File: LICENSE
Requires-Dist: scanpy
Requires-Dist: pandas
Requires-Dist: numpy
Requires-Dist: scipy
Requires-Dist: rpy2
